AUTHORS
CONTRIBUTING.md
LICENSE
MANIFEST.in
README.md
setup.cfg
setup.py
doas/__init__.py
doas/constants.py
doas/models.py
doas/ops.py
doas/platforms.py
doas/sessions.py
doas/settings.py
doas/utils.py
doas.egg-info/PKG-INFO
doas.egg-info/SOURCES.txt
doas.egg-info/dependency_links.txt
doas.egg-info/not-zip-safe
doas.egg-info/requires.txt
doas.egg-info/top_level.txt
doas/io/__init__.py
doas/io/result_reader.py