Metadata-Version: 2.1
Name: doas
Version: 0.1.0
Summary: DOAS processing utility library
Home-page: https://gitlab.com/bpptkg/doas
Author: Indra Rudianto
Author-email: indrarudianto.official@gmail.com
License: MIT
Platform: UNKNOWN
Classifier: Development Status :: 5 - Production/Stable
Classifier: Environment :: Console
Classifier: Operating System :: POSIX :: Linux
Classifier: Intended Audience :: Science/Research
Classifier: Natural Language :: Indonesian
Classifier: Programming Language :: Python :: 3.5
Classifier: Programming Language :: Python :: 3.6
Classifier: Programming Language :: Python :: 3.7
Classifier: Programming Language :: Python :: 3.8
Requires-Python: >=3.5
